{
    "profile": [
        {
            "symbol": "AEP",
            "price": 101.85,
            "beta": 0.41,
            "volAvg": 4165792,
            "mktCap": 54407760750,
            "lastDiv": 3.67,
            "range": "85.93-110.48",
            "changes": -0.98,
            "companyName": "American Electric Power Company, Inc.",
            "currency": "USD",
            "cik": "0000004904",
            "isin": "US0255371017",
            "cusip": "025537101",
            "exchange": "NASDAQ Global Select",
            "exchangeShortName": "NASDAQ",
            "industry": "Regulated Electric",
            "website": "https://www.aep.com",
            "description": "American Electric Power Company, Inc., an electric public utility holding company, engages in the generation, transmission, and distribution of electricity for sale to retail and wholesale customers in the United States. It operates through Vertically Integrated Utilities, Transmission and Distribution Utilities, AEP Transmission Holdco, and Generation & Marketing segments. The company generates electricity using coal and lignite, natural gas, nuclear, hydro, solar, wind, and other energy sources. It also supplies and markets electric power at wholesale to other electric utility companies, rural electric cooperatives, municipalities, and other market participants. American Electric Power Company, Inc. was incorporated in 1906 and is headquartered in Columbus, Ohio.",
            "ceo": "Mr. William J. Fehrman",
            "sector": "Utilities",
            "country": "US",
            "fullTimeEmployees": "16330",
            "phone": "614 716 1000",
            "address": "1 Riverside Plaza",
            "city": "Columbus",
            "state": "OH",
            "zip": "43215-2373",
            "dcfDiff": -15.34969,
            "dcf": 121.69969436117104,
            "image": "https://images.financialmodelingprep.com/symbol/AEP.png",
            "ipoDate": "1962-01-02",
            "defaultImage": false,
            "isEtf": false,
            "isActivelyTrading": true,
            "isAdr": false,
            "isFund": false
        }
    ],
    "ratios": [
        {
            "symbol": "AEP",
            "date": "2024-12-31",
            "calendarYear": "2024",
            "period": "FY",
            "currentRatio": 0.44497398015266004,
            "quickRatio": 0.31313752469387285,
            "cashRatio": 0.015596534786652625,
            "daysOfSalesOutstanding": 48.71096225908028,
            "daysOfInventoryOutstanding": 86.21085465612691,
            "operatingCycle": 134.92181691520722,
            "daysOfPayablesOutstanding": 132.58104497755255,
            "cashConversionCycle": 2.340771937654665,
            "grossProfitMargin": 0.631799120747618,
            "operatingProfitMargin": 0.21822090835796829,
            "pretaxProfitMargin": 0.144153782965626,
            "netProfitMargin": 0.15045154224113014,
            "effectiveTaxRate": -0.013788736853213268,
            "returnOnAssets": 0.02806301717867888,
            "returnOnEquity": 0.11012180909893927,
            "returnOnCapitalEmployed": 0.046414712588141144,
            "netIncomePerEBT": 1.0436877836012521,
            "ebtPerEbit": 0.6605864857328748,
            "ebitPerRevenue": 0.21822090835796829,
            "debtRatio": 0.43282742157138143,
            "debtEquityRatio": 1.6984538186892717,
            "longTermDebtToCapitalization": 0.5933109539996015,
            "totalDebtToCapitalization": 0.6294174118993324,
            "interestCoverage": 2.3102855915825637,
            "cashFlowToDebtRatio": 0.14868626919681488,
            "companyEquityMultiplier": 3.92409014318693,
            "receivablesTurnover": 7.4931798320604885,
            "payablesTurnover": 2.753033060357901,
            "inventoryTurnover": 4.23380560900239,
            "fixedAssetTurnover": 0.23761833444383262,
            "assetTurnover": 0.18652528754874448,
            "operatingCashFlowPerShare": 12.83605746581609,
            "freeCashFlowPerShare": 12.572141348145253,
            "cashPerShare": 0.7891073053732008,
            "payoutRatio": 0.6416703178187456,
            "operatingCashFlowSalesRatio": 0.3450228940282841,
            "freeCashFlowOperatingCashFlowRatio": 0.9794394720985259,
            "cashFlowCoverageRatios": 0.14868626919681488,
            "shortTermCoverageRatios": 1.1613811702055028,
            "capitalExpenditureCoverageRatio": 48.63688348820586,
            "dividendPaidAndCapexCoverageRatio": 3.329239651629318,
            "dividendPayoutRatio": 0.6416703178187456,
            "priceBookValueRatio": 1.814534220806271,
            "priceToBookRatio": 1.814534220806271,
            "priceToSalesRatio": 2.4790681719034753,
            "priceEarningsRatio": 16.477519173118534,
            "priceToFreeCashFlowsRatio": 7.336061331636757,
            "priceToOperatingCashFlowsRatio": 7.185228037940714,
            "priceCashFlowRatio": 7.185228037940714,
            "priceEarningsToGrowthRatio": 0.5238375498319775,
            "priceSalesRatio": 2.4790681719034753,
            "dividendYield": 0.038942167875948716,
            "enterpriseValueMultiple": 11.662696442373278,
            "priceFairValue": 1.814534220806271
        },
        {
            "symbol": "AEP",
            "date": "2023-12-31",
            "calendarYear": "2023",
            "period": "FY",
            "currentRatio": 0.5250612935529542,
            "quickRatio": 0.36280603612003176,
            "cashRatio": 0.02849718567630098,
            "daysOfSalesOutstanding": 46.12325692882317,
            "daysOfInventoryOutstanding": 87.33958444733022,
            "operatingCycle": 133.4628413761534,
            "daysOfPayablesOutstanding": 94.44943090672982,
            "cashConversionCycle": 39.013410469423576,
            "grossProfitMargin": 0.5862145261638474,
            "operatingProfitMargin": 0.18734294579687394,
            "pretaxProfitMargin": 0.11635576300026867,
            "netProfitMargin": 0.11632415460718669,
            "effectiveTaxRate": 0.024720423778693348,
            "returnOnAssets": 0.022838318646311695,
            "returnOnEquity": 0.08746093548859851,
            "returnOnCapitalEmployed": 0.04178828771662648,
            "netIncomePerEBT": 0.999728346991443,
            "ebtPerEbit": 0.6210843034699961,
            "ebitPerRevenue": 0.18734294579687394,
            "debtRatio": 0.45104153737950436,
            "debtEquityRatio": 1.7272950524226929,
            "longTermDebtToCapitalization": 0.5986177928565296,
            "totalDebtToCapitalization": 0.6333363348011479,
            "interestCoverage": 1.9681221982400796,
            "cashFlowToDebtRatio": 0.11493630828852174,
            "companyEquityMultiplier": 3.829569805162655,
            "receivablesTurnover": 7.913578188185267,
            "payablesTurnover": 3.86450184501845,
            "inventoryTurnover": 4.179090183559457,
            "fixedAssetTurnover": 0.24552342666749447,
            "assetTurnover": 0.1963334160771172,
            "operatingCashFlowPerShare": 9.65921070492616,
            "freeCashFlowPerShare": -4.8068651014120185,
            "cashPerShare": 1.049134972220143,
            "payoutRatio": 0.7972465015171414,
            "operatingCashFlowSalesRatio": 0.26404597967580323,
            "freeCashFlowOperatingCashFlowRatio": -0.49764574438370374,
            "cashFlowCoverageRatios": 0.11493630828852174,
            "shortTermCoverageRatios": 0.9420189072866352,
            "capitalExpenditureCoverageRatio": 0.6677146473056684,
            "dividendPaidAndCapexCoverageRatio": 0.5408712730254993,
            "dividendPayoutRatio": 0.7972465015171414,
            "priceBookValueRatio": 1.6693412228940812,
            "priceToBookRatio": 1.6693412228940812,
            "priceToSalesRatio": 2.2202450204685418,
            "priceEarningsRatio": 19.086706694461302,
            "priceToFreeCashFlowsRatio": -16.89666722208235,
            "priceToOperatingCashFlowsRatio": 8.408554537336897,
            "priceCashFlowRatio": 8.408554537336897,
            "priceEarningsToGrowthRatio": -3.4432418876808195,
            "priceSalesRatio": 2.2202450204685418,
            "dividendYield": 0.04176972561476472,
            "enterpriseValueMultiple": 11.860127877716382,
            "priceFairValue": 1.6693412228940812
        },
        {
            "symbol": "AEP",
            "date": "2022-12-31",
            "calendarYear": "2022",
            "period": "FY",
            "currentRatio": 0.6465601274077736,
            "quickRatio": 0.5571756112964564,
            "cashRatio": 0.03496849128876807,
            "daysOfSalesOutstanding": 48.661091168308765,
            "daysOfInventoryOutstanding": 56.93655433493465,
            "operatingCycle": 105.59764550324341,
            "daysOfPayablesOutstanding": 116.78530782408683,
            "cashConversionCycle": -11.187662320843415,
            "grossProfitMargin": 0.5749739046309733,
            "operatingProfitMargin": 0.17733139845719087,
            "pretaxProfitMargin": 0.1232414267165661,
            "netProfitMargin": 0.11747753252374042,
            "effectiveTaxRate": 0.0022310361923648984,
            "returnOnAssets": 0.024684014233535254,
            "returnOnEquity": 0.09656223057413345,
            "returnOnCapitalEmployed": 0.04413956553699526,
            "netIncomePerEBT": 0.9532308709304247,
            "ebtPerEbit": 0.6949780342837454,
            "ebitPerRevenue": 0.17733139845719087,
            "debtRatio": 0.43223022721874754,
            "debtEquityRatio": 1.6908560522989613,
            "longTermDebtToCapitalization": 0.5901583386364455,
            "totalDebtToCapitalization": 0.6283710534624699,
            "interestCoverage": 2.4945920779313804,
            "cashFlowToDebtRatio": 0.1308901171525954,
            "companyEquityMultiplier": 3.911933839470314,
            "receivablesTurnover": 7.500859336210518,
            "payablesTurnover": 3.1253931406320206,
            "inventoryTurnover": 6.4106443437524,
            "fixedAssetTurnover": 0.2730442568182861,
            "assetTurnover": 0.21011689387114926,
            "operatingCashFlowPerShare": 10.331314268643391,
            "freeCashFlowPerShare": -2.9001140129300773,
            "cashPerShare": 1.3615531228853213,
            "payoutRatio": 0.7130721220527045,
            "operatingCashFlowSalesRatio": 0.269253290562387,
            "freeCashFlowOperatingCashFlowRatio": -0.28071104387291984,
            "cashFlowCoverageRatios": 0.1308901171525954,
            "shortTermCoverageRatios": 0.7963855421686747,
            "capitalExpenditureCoverageRatio": 0.7808162542082571,
            "dividendPaidAndCapexCoverageRatio": 0.6282075651016917,
            "dividendPayoutRatio": 0.7130721220527045,
            "priceBookValueRatio": 2.034009089233847,
            "priceToBookRatio": 2.034009089233847,
            "priceToSalesRatio": 2.474573831956007,
            "priceEarningsRatio": 21.064230570691745,
            "priceToFreeCashFlowsRatio": -32.74009214005659,
            "priceToOperatingCashFlowsRatio": 9.190505441130863,
            "priceCashFlowRatio": 9.190505441130863,
            "priceEarningsToGrowthRatio": -2.2758527377464763,
            "priceSalesRatio": 2.474573831956007,
            "dividendYield": 0.03385227481533817,
            "enterpriseValueMultiple": 12.45956080829884,
            "priceFairValue": 2.034009089233847
        },
        {
            "symbol": "AEP",
            "date": "2021-12-31",
            "calendarYear": "2021",
            "period": "FY",
            "currentRatio": 0.6284210611023039,
            "quickRatio": 0.5488182703372577,
            "cashRatio": 0.032462359274787356,
            "daysOfSalesOutstanding": 41.46679966650786,
            "daysOfInventoryOutstanding": 54.8045718796011,
            "operatingCycle": 96.27137154610895,
            "daysOfPayablesOutstanding": 113.8308465263126,
            "cashConversionCycle": -17.559474980203646,
            "grossProfitMargin": 0.607664363982849,
            "operatingProfitMargin": 0.20315030967127204,
            "pretaxProfitMargin": 0.14958909004287757,
            "netProfitMargin": 0.14817174845164363,
            "effectiveTaxRate": 0.04598112982204706,
            "returnOnAssets": 0.028380710561466065,
            "returnOnEquity": 0.1109115061605121,
            "returnOnCapitalEmployed": 0.04533771032136307,
            "netIncomePerEBT": 0.9905251005215175,
            "ebtPerEbit": 0.7363468472429865,
            "ebitPerRevenue": 0.20315030967127204,
            "debtRatio": 0.41815265881665864,
            "debtEquityRatio": 1.6341360126954692,
            "longTermDebtToCapitalization": 0.5825130876411353,
            "totalDebtToCapitalization": 0.6203688817963823,
            "interestCoverage": 2.84488366274706,
            "cashFlowToDebtRatio": 0.10474673271702097,
            "companyEquityMultiplier": 3.9079890519408735,
            "receivablesTurnover": 8.80222257168318,
            "payablesTurnover": 3.206512216489828,
            "inventoryTurnover": 6.6600283057015774,
            "fixedAssetTurnover": 0.2522093854574074,
            "assetTurnover": 0.19153928368961784,
            "operatingCashFlowPerShare": 7.671787937580237,
            "freeCashFlowPerShare": -3.844385101042186,
            "cashPerShare": 1.2462984232564784,
            "payoutRatio": 0.6107069651541337,
            "operatingCashFlowSalesRatio": 0.2286743687470224,
            "freeCashFlowOperatingCashFlowRatio": -0.501106799656241,
            "cashFlowCoverageRatios": 0.10474673271702097,
            "shortTermCoverageRatios": 0.8053819371617937,
            "capitalExpenditureCoverageRatio": 0.6661751184053017,
            "dividendPaidAndCapexCoverageRatio": 0.5271980888571586,
            "dividendPayoutRatio": 0.6107069651541337,
            "priceBookValueRatio": 1.9850693653910274,
            "priceToBookRatio": 1.9850693653910274,
            "priceToSalesRatio": 2.6519448599148405,
            "priceEarningsRatio": 17.897776651939232,
            "priceToFreeCashFlowsRatio": -23.14284278541212,
            "priceToOperatingCashFlowsRatio": 11.597035883145393,
            "priceCashFlowRatio": 11.597035883145393,
            "priceEarningsToGrowthRatio": 1.4993609119737799,
            "priceSalesRatio": 2.6519448599148405,
            "dividendYield": 0.034121945816547185,
            "enterpriseValueMultiple": 11.955331649405098,
            "priceFairValue": 1.9850693653910274
        },
        {
            "symbol": "AEP",
            "date": "2020-12-31",
            "calendarYear": "2020",
            "period": "FY",
            "currentRatio": 0.43836320227265857,
            "quickRatio": 0.30639588181369437,
            "cashRatio": 0.03955997461392003,
            "daysOfSalesOutstanding": 44.27415624895264,
            "daysOfInventoryOutstanding": 88.87381275440977,
            "operatingCycle": 133.14796900336242,
            "daysOfPayablesOutstanding": 115.99050203527815,
            "cashConversionCycle": 17.157466968084265,
            "grossProfitMargin": 0.6393672286087744,
            "operatingProfitMargin": 0.20026812347085832,
            "pretaxProfitMargin": 0.14385494520226563,
            "netProfitMargin": 0.1474746120588531,
            "effectiveTaxRate": 0.018871441218955315,
            "returnOnAssets": 0.027243391301332884,
            "returnOnEquity": 0.10705613866059394,
            "returnOnCapitalEmployed": 0.042180981356901334,
            "netIncomePerEBT": 1.0251619216252736,
            "ebtPerEbit": 0.7183117448204305,
            "ebitPerRevenue": 0.20026812347085832,
            "debtRatio": 0.4263582689840658,
            "debtEquityRatio": 1.6754254071597838,
            "longTermDebtToCapitalization": 0.5851429125123897,
            "totalDebtToCapitalization": 0.6262276655802584,
            "interestCoverage": 2.5630093506047866,
            "cashFlowToDebtRatio": 0.11131957655054238,
            "companyEquityMultiplier": 3.9296186541708638,
            "receivablesTurnover": 8.244087091069849,
            "payablesTurnover": 3.1468093817628824,
            "inventoryTurnover": 4.106946564885496,
            "fixedAssetTurnover": 0.23033751235177866,
            "assetTurnover": 0.18473275447885762,
            "operatingCashFlowPerShare": 7.732013515266717,
            "freeCashFlowPerShare": -5.00909566118573,
            "cashPerShare": 1.1972527384776008,
            "payoutRatio": 0.6476523794372983,
            "operatingCashFlowSalesRatio": 0.2569226128632235,
            "freeCashFlowOperatingCashFlowRatio": -0.6478384513031908,
            "cashFlowCoverageRatios": 0.11131957655054238,
            "shortTermCoverageRatios": 0.8395540368861436,
            "capitalExpenditureCoverageRatio": 0.6068556048131729,
            "dividendPaidAndCapexCoverageRatio": 0.49514914286452477,
            "dividendPayoutRatio": 0.6476523794372983,
            "priceBookValueRatio": 2.0085960434438395,
            "priceToBookRatio": 2.0085960434438395,
            "priceToSalesRatio": 2.766930752368536,
            "priceEarningsRatio": 18.762081918644608,
            "priceToFreeCashFlowsRatio": -16.62375918376626,
            "priceToOperatingCashFlowsRatio": 10.769510404448328,
            "priceCashFlowRatio": 10.769510404448328,
            "priceEarningsToGrowthRatio": 1.3269908847914098,
            "priceSalesRatio": 2.766930752368536,
            "dividendYield": 0.03451921712343133,
            "enterpriseValueMultiple": 12.111609756088185,
            "priceFairValue": 2.0085960434438395
        }
    ],
    "income_statement": [
        {
            "date": "2024-12-31",
            "symbol": "AEP",
            "reportedCurrency": "USD",
            "cik": "0000004904",
            "fillingDate": "2025-02-13",
            "acceptedDate": "2025-02-13 10:25:44",
            "calendarYear": "2024",
            "period": "FY",
            "revenue": 19721300000,
            "costOfRevenue": 7261400000,
            "grossProfit": 12459900000,
            "grossProfitRatio": 0.6317991207,
            "researchAndDevelopmentExpenses": 0,
            "generalAndAdministrativeExpenses": 0,
            "sellingAndMarketingExpenses": 0,
            "sellingGeneralAndAdministrativeExpenses": 0,
            "otherExpenses": 8156300000,
            "operatingExpenses": 8156300000,
            "costAndExpenses": 15417700000,
            "interestIncome": 0,
            "interestExpense": 1862800000,
            "depreciationAndAmortization": 3392800000,
            "ebitda": 8098500000,
            "ebitdaratio": 0.4106473711,
            "operatingIncome": 4303600000,
            "operatingIncomeRatio": 0.2182209084,
            "totalOtherIncomeExpensesNet": -1460700000,
            "incomeBeforeTax": 2842900000,
            "incomeBeforeTaxRatio": 0.144153783,
            "incomeTaxExpense": -39200000,
            "netIncome": 2967100000,
            "netIncomeRatio": 0.1504515422,
            "eps": 5.6,
            "epsdiluted": 5.58,
            "weightedAverageShsOut": 530092672,
            "weightedAverageShsOutDil": 531337703,
            "link": "https://www.sec.gov/Archives/edgar/data/4904/000000490425000027/0000004904-25-000027-index.htm",
            "finalLink": "https://www.sec.gov/Archives/edgar/data/4904/000000490425000027/aep-20241231.htm"
        },
        {
            "date": "2023-12-31",
            "symbol": "AEP",
            "reportedCurrency": "USD",
            "cik": "0000004904",
            "fillingDate": "2024-02-26",
            "acceptedDate": "2024-02-26 16:44:18",
            "calendarYear": "2023",
            "period": "FY",
            "revenue": 18982300000,
            "costOfRevenue": 7854600000,
            "grossProfit": 11127700000,
            "grossProfitRatio": 0.5862145262,
            "researchAndDevelopmentExpenses": 0,
            "generalAndAdministrativeExpenses": 0,
            "sellingAndMarketingExpenses": 0,
            "sellingGeneralAndAdministrativeExpenses": 0,
            "otherExpenses": 7571500000,
            "operatingExpenses": 7571500000,
            "costAndExpenses": 15426100000,
            "interestIncome": 0,
            "interestExpense": 1806900000,
            "depreciationAndAmortization": 3187000000,
            "ebitda": 7202600000,
            "ebitdaratio": 0.3794376867,
            "operatingIncome": 3556200000,
            "operatingIncomeRatio": 0.1873429458,
            "totalOtherIncomeExpensesNet": -1347500000,
            "incomeBeforeTax": 2208700000,
            "incomeBeforeTaxRatio": 0.116355763,
            "incomeTaxExpense": 54600000,
            "netIncome": 2208100000,
            "netIncomeRatio": 0.1163241546,
            "eps": 4.26,
            "epsdiluted": 4.24,
            "weightedAverageShsOut": 518903682,
            "weightedAverageShsOutDil": 520206258,
            "link": "https://www.sec.gov/Archives/edgar/data/4904/000000490424000020/0000004904-24-000020-index.htm",
            "finalLink": "https://www.sec.gov/Archives/edgar/data/4904/000000490424000020/aep-20231231.htm"
        },
        {
            "date": "2022-12-31",
            "symbol": "AEP",
            "reportedCurrency": "USD",
            "cik": "0000004904",
            "fillingDate": "2023-02-23",
            "acceptedDate": "2023-02-23 08:24:42",
            "calendarYear": "2022",
            "period": "FY",
            "revenue": 19639500000,
            "costOfRevenue": 8347300000,
            "grossProfit": 11292200000,
            "grossProfitRatio": 0.5749739046,
            "researchAndDevelopmentExpenses": 0,
            "generalAndAdministrativeExpenses": 0,
            "sellingAndMarketingExpenses": 0,
            "sellingGeneralAndAdministrativeExpenses": 0,
            "otherExpenses": 7809500000,
            "operatingExpenses": 7809500000,
            "costAndExpenses": 16156800000,
            "interestIncome": 0,
            "interestExpense": 1396100000,
            "depreciationAndAmortization": 3285700000,
            "ebitda": 7102200000,
            "ebitdaratio": 0.361628351,
            "operatingIncome": 3482700000,
            "operatingIncomeRatio": 0.1773313985,
            "totalOtherIncomeExpensesNet": -1062300000,
            "incomeBeforeTax": 2420400000,
            "incomeBeforeTaxRatio": 0.1232414267,
            "incomeTaxExpense": 5400000,
            "netIncome": 2307200000,
            "netIncomeRatio": 0.1174775325,
            "eps": 4.51,
            "epsdiluted": 4.49,
            "weightedAverageShsOut": 511841946,
            "weightedAverageShsOutDil": 513484609,
            "link": "https://www.sec.gov/Archives/edgar/data/4904/000000490423000011/0000004904-23-000011-index.htm",
            "finalLink": "https://www.sec.gov/Archives/edgar/data/4904/000000490423000011/aep-20221231.htm"
        },
        {
            "date": "2021-12-31",
            "symbol": "AEP",
            "reportedCurrency": "USD",
            "cik": "0000004904",
            "fillingDate": "2022-02-24",
            "acceptedDate": "2022-02-24 07:46:11",
            "calendarYear": "2021",
            "period": "FY",
            "revenue": 16792000000,
            "costOfRevenue": 6588100000,
            "grossProfit": 10203900000,
            "grossProfitRatio": 0.607664364,
            "researchAndDevelopmentExpenses": 0,
            "generalAndAdministrativeExpenses": 0,
            "sellingAndMarketingExpenses": 0,
            "sellingGeneralAndAdministrativeExpenses": 0,
            "otherExpenses": 6792600000,
            "operatingExpenses": 6792600000,
            "costAndExpenses": 13380700000,
            "interestIncome": 0,
            "interestExpense": 1199100000,
            "depreciationAndAmortization": 3046400000,
            "ebitda": 6757400000,
            "ebitdaratio": 0.402417818,
            "operatingIncome": 3411300000,
            "operatingIncomeRatio": 0.2031503097,
            "totalOtherIncomeExpensesNet": -899400000,
            "incomeBeforeTax": 2511900000,
            "incomeBeforeTaxRatio": 0.14958909,
            "incomeTaxExpense": 115500000,
            "netIncome": 2488100000,
            "netIncomeRatio": 0.1481717485,
            "eps": 4.97,
            "epsdiluted": 4.96,
            "weightedAverageShsOut": 500522177,
            "weightedAverageShsOutDil": 501784032,
            "link": "https://www.sec.gov/Archives/edgar/data/4904/000000490422000024/0000004904-22-000024-index.htm",
            "finalLink": "https://www.sec.gov/Archives/edgar/data/4904/000000490422000024/aep-20211231.htm"
        },
        {
            "date": "2020-12-31",
            "symbol": "AEP",
            "reportedCurrency": "USD",
            "cik": "0000004904",
            "fillingDate": "2021-02-25",
            "acceptedDate": "2021-02-25 08:27:36",
            "calendarYear": "2020",
            "period": "FY",
            "revenue": 14918500000,
            "costOfRevenue": 5380100000,
            "grossProfit": 9538400000,
            "grossProfitRatio": 0.6393672286,
            "researchAndDevelopmentExpenses": 0,
            "generalAndAdministrativeExpenses": 0,
            "sellingAndMarketingExpenses": 0,
            "sellingGeneralAndAdministrativeExpenses": 0,
            "otherExpenses": 6550700000,
            "operatingExpenses": 6550700000,
            "costAndExpenses": 11930800000,
            "interestIncome": 0,
            "interestExpense": 1165700000,
            "depreciationAndAmortization": 2906800000,
            "ebitda": 6218600000,
            "ebitdaratio": 0.416838154,
            "operatingIncome": 2987700000,
            "operatingIncomeRatio": 0.2002681235,
            "totalOtherIncomeExpensesNet": -841600000,
            "incomeBeforeTax": 2146100000,
            "incomeBeforeTaxRatio": 0.1438549452,
            "incomeTaxExpense": 40500000,
            "netIncome": 2200100000,
            "netIncomeRatio": 0.1474746121,
            "eps": 4.44,
            "epsdiluted": 4.42,
            "weightedAverageShsOut": 495718223,
            "weightedAverageShsOutDil": 497226867,
            "link": "https://www.sec.gov/Archives/edgar/data/4904/000000490421000010/0000004904-21-000010-index.htm",
            "finalLink": "https://www.sec.gov/Archives/edgar/data/4904/000000490421000010/aep-20201231.htm"
        }
    ],
    "balance_sheet": [
        {
            "date": "2024-12-31",
            "symbol": "AEP",
            "reportedCurrency": "USD",
            "cik": "0000004904",
            "fillingDate": "2025-02-13",
            "acceptedDate": "2025-02-13 10:25:44",
            "calendarYear": "2024",
            "period": "FY",
            "cashAndCashEquivalents": 202900000,
            "shortTermInvestments": 215400000,
            "cashAndShortTermInvestments": 418300000,
            "netReceivables": 2631900000,
            "inventory": 1715100000,
            "otherCurrentAssets": 1023500000,
            "totalCurrentAssets": 5788800000,
            "propertyPlantEquipmentNet": 82995700000,
            "goodwill": 52500000,
            "intangibleAssets": 0,
            "goodwillAndIntangibleAssets": 52500000,
            "longTermInvestments": 4949400000,
            "taxAssets": 2651900000,
            "otherNonCurrentAssets": 9291600000,
            "totalNonCurrentAssets": 99941099999,
            "otherAssets": 0,
            "totalAssets": 105729900000,
            "accountPayables": 2637600000,
            "shortTermDebt": 5950700000,
            "taxPayables": 1922100000,
            "deferredRevenue": 454700000,
            "otherCurrentLiabilities": 2044200000,
            "totalCurrentLiabilities": 13009300000,
            "longTermDebt": 39812100000,
            "deferredRevenueNonCurrent": 0,
            "deferredTaxLiabilitiesNonCurrent": 9972400000,
            "otherNonCurrentLiabilities": 13298100000,
            "totalNonCurrentLiabilities": 65696700000,
            "otherLiabilities": 0,
            "capitalLeaseObligations": 596200000,
            "totalLiabilities": 76091900000,
            "preferredStock": 0,
            "commonStock": 3471600000,
            "retainedEarnings": 13869200000,
            "accumulatedOtherComprehensiveIncomeLoss": -3100000,
            "othertotalStockholdersEquity": 34200500000,
            "totalStockholdersEquity": 26943800000,
            "totalEquity": 26986100000,
            "totalLiabilitiesAndStockholdersEquity": 103078000000,
            "minorityInterest": 42300000,
            "totalLiabilitiesAndTotalEquity": 103078000000,
            "totalInvestments": 5164800000,
            "totalDebt": 45762800000,
            "netDebt": 45559900000,
            "link": "https://www.sec.gov/Archives/edgar/data/4904/000000490425000027/0000004904-25-000027-index.htm",
            "finalLink": "https://www.sec.gov/Archives/edgar/data/4904/000000490425000027/aep-20241231.htm"
        },
        {
            "date": "2023-12-31",
            "symbol": "AEP",
            "reportedCurrency": "USD",
            "cik": "0000004904",
            "fillingDate": "2024-02-26",
            "acceptedDate": "2024-02-26 16:44:18",
            "calendarYear": "2023",
            "period": "FY",
            "cashAndCashEquivalents": 330100000,
            "shortTermInvestments": 214300000,
            "cashAndShortTermInvestments": 544400000,
            "netReceivables": 2398700000,
            "inventory": 1879500000,
            "otherCurrentAssets": 1259500000,
            "totalCurrentAssets": 6082100000,
            "propertyPlantEquipmentNet": 77313600000,
            "goodwill": 52500000,
            "intangibleAssets": 0,
            "goodwillAndIntangibleAssets": 52500000,
            "longTermInvestments": 4196500000,
            "taxAssets": 0,
            "otherNonCurrentAssets": 9039300000,
            "totalNonCurrentAssets": 90601900000,
            "otherAssets": 0,
            "totalAssets": 96684000000,
            "accountPayables": 2032500000,
            "shortTermDebt": 5436400000,
            "taxPayables": 1800100000,
            "deferredRevenue": 423700000,
            "otherCurrentLiabilities": 1890900000,
            "totalCurrentLiabilities": 11583600000,
            "longTermDebt": 38312000000,
            "deferredRevenueNonCurrent": -139900000,
            "deferredTaxLiabilitiesNonCurrent": 9415700000,
            "otherNonCurrentLiabilities": 12086800000,
            "totalNonCurrentLiabilities": 59814500000,
            "otherLiabilities": 0,
            "capitalLeaseObligations": 775000000,
            "totalLiabilities": 71398100000,
            "preferredStock": 0,
            "commonStock": 3427900000,
            "retainedEarnings": 12800400000,
            "accumulatedOtherComprehensiveIncomeLoss": -55500000,
            "othertotalStockholdersEquity": 9073900000,
            "totalStockholdersEquity": 25246700000,
            "totalEquity": 25285900000,
            "totalLiabilitiesAndStockholdersEquity": 96684000000,
            "minorityInterest": 39200000,
            "totalLiabilitiesAndTotalEquity": 96684000000,
            "totalInvestments": 4410800000,
            "totalDebt": 43608500000,
            "netDebt": 43278400000,
            "link": "https://www.sec.gov/Archives/edgar/data/4904/000000490424000020/0000004904-24-000020-index.htm",
            "finalLink": "https://www.sec.gov/Archives/edgar/data/4904/000000490424000020/aep-20231231.htm"
        },
        {
            "date": "2022-12-31",
            "symbol": "AEP",
            "reportedCurrency": "USD",
            "cik": "0000004904",
            "fillingDate": "2023-02-23",
            "acceptedDate": "2023-02-23 08:24:42",
            "calendarYear": "2022",
            "period": "FY",
            "cashAndCashEquivalents": 509400000,
            "shortTermInvestments": 187500000,
            "cashAndShortTermInvestments": 696900000,
            "netReceivables": 2618300000,
            "inventory": 1302100000,
            "otherCurrentAssets": 2110000000,
            "totalCurrentAssets": 9418700000,
            "propertyPlantEquipmentNet": 71927900000,
            "goodwill": 52500000,
            "intangibleAssets": 0,
            "goodwillAndIntangibleAssets": 52500000,
            "longTermInvestments": 3787200000,
            "taxAssets": 8493300000,
            "otherNonCurrentAssets": -210200000,
            "totalNonCurrentAssets": 84050700000,
            "otherAssets": 0,
            "totalAssets": 93469400000,
            "accountPayables": 2670800000,
            "shortTermDebt": 6810900000,
            "taxPayables": 1672800000,
            "deferredRevenue": 370000000,
            "otherCurrentLiabilities": 2111800000,
            "totalCurrentLiabilities": 14567400000,
            "longTermDebt": 35126600000,
            "deferredRevenueNonCurrent": 8493300000,
            "deferredTaxLiabilitiesNonCurrent": 8493300000,
            "otherNonCurrentLiabilities": 20888000000,
            "totalNonCurrentLiabilities": 54779600000,
            "otherLiabilities": 0,
            "capitalLeaseObligations": 891800000,
            "totalLiabilities": 69347000000,
            "preferredStock": 0,
            "commonStock": 3413100000,
            "retainedEarnings": 12345600000,
            "accumulatedOtherComprehensiveIncomeLoss": 83700000,
            "othertotalStockholdersEquity": 8051000000,
            "totalStockholdersEquity": 23893400000,
            "totalEquity": 24122400000,
            "totalLiabilitiesAndStockholdersEquity": 93469400000,
            "minorityInterest": 229000000,
            "totalLiabilitiesAndTotalEquity": 93469400000,
            "totalInvestments": 3974700000,
            "totalDebt": 40400300000,
            "netDebt": 39890900000,
            "link": "https://www.sec.gov/Archives/edgar/data/4904/000000490423000011/0000004904-23-000011-index.htm",
            "finalLink": "https://www.sec.gov/Archives/edgar/data/4904/000000490423000011/aep-20221231.htm"
        },
        {
            "date": "2021-12-31",
            "symbol": "AEP",
            "reportedCurrency": "USD",
            "cik": "0000004904",
            "fillingDate": "2022-02-24",
            "acceptedDate": "2022-02-24 07:46:11",
            "calendarYear": "2021",
            "period": "FY",
            "cashAndCashEquivalents": 403400000,
            "shortTermInvestments": 220400000,
            "cashAndShortTermInvestments": 623800000,
            "netReceivables": 1907700000,
            "inventory": 989200000,
            "otherCurrentAssets": 4288500000,
            "totalCurrentAssets": 7809200000,
            "propertyPlantEquipmentNet": 66579600000,
            "goodwill": 52500000,
            "intangibleAssets": 0,
            "goodwillAndIntangibleAssets": 52500000,
            "longTermInvestments": 4419800000,
            "taxAssets": 8202500000,
            "otherNonCurrentAssets": 605100000,
            "totalNonCurrentAssets": 79859500000,
            "otherAssets": 0,
            "totalAssets": 87668700000,
            "accountPayables": 2054600000,
            "shortTermDebt": 4865400000,
            "taxPayables": 1586400000,
            "deferredRevenue": 321600000,
            "otherCurrentLiabilities": 3598700000,
            "totalCurrentLiabilities": 12426700000,
            "longTermDebt": 31989600000,
            "deferredRevenueNonCurrent": 0,
            "deferredTaxLiabilitiesNonCurrent": 8202500000,
            "otherNonCurrentLiabilities": 20572200000,
            "totalNonCurrentLiabilities": 52561800000,
            "otherLiabilities": 0,
            "capitalLeaseObligations": 786500000,
            "totalLiabilities": 64988500000,
            "preferredStock": 0,
            "commonStock": 3408700000,
            "retainedEarnings": 11667100000,
            "accumulatedOtherComprehensiveIncomeLoss": 184800000,
            "othertotalStockholdersEquity": 7172600000,
            "totalStockholdersEquity": 22433200000,
            "totalEquity": 22680200000,
            "totalLiabilitiesAndStockholdersEquity": 87668700000,
            "minorityInterest": 247000000,
            "totalLiabilitiesAndTotalEquity": 87668700000,
            "totalInvestments": 4640200000,
            "totalDebt": 36658900000,
            "netDebt": 36255500000,
            "link": "https://www.sec.gov/Archives/edgar/data/4904/000000490422000024/0000004904-22-000024-index.htm",
            "finalLink": "https://www.sec.gov/Archives/edgar/data/4904/000000490422000024/aep-20211231.htm"
        },
        {
            "date": "2020-12-31",
            "symbol": "AEP",
            "reportedCurrency": "USD",
            "cik": "0000004904",
            "fillingDate": "2021-02-25",
            "acceptedDate": "2021-02-25 08:27:36",
            "calendarYear": "2020",
            "period": "FY",
            "cashAndCashEquivalents": 392700000,
            "shortTermInvestments": 200800000,
            "cashAndShortTermInvestments": 593500000,
            "netReceivables": 1809600000,
            "inventory": 1310000000,
            "otherCurrentAssets": 638400000,
            "totalCurrentAssets": 4351500000,
            "propertyPlantEquipmentNet": 64768000000,
            "goodwill": 52500000,
            "intangibleAssets": 0,
            "goodwillAndIntangibleAssets": 52500000,
            "longTermInvestments": 3963700000,
            "taxAssets": 1017600000,
            "otherNonCurrentAssets": 6603900000,
            "totalNonCurrentAssets": 76405700000,
            "otherAssets": 0,
            "totalAssets": 80757200000,
            "accountPayables": 1709700000,
            "shortTermDebt": 4864800000,
            "taxPayables": 1476400000,
            "deferredRevenue": 335600000,
            "otherCurrentLiabilities": 1875800000,
            "totalCurrentLiabilities": 9926700000,
            "longTermDebt": 29855800000,
            "deferredRevenueNonCurrent": 0,
            "deferredTaxLiabilitiesNonCurrent": 8240900000,
            "otherNonCurrentLiabilities": 20200200000,
            "totalNonCurrentLiabilities": 50056000000,
            "otherLiabilities": 0,
            "capitalLeaseObligations": 1168800000,
            "totalLiabilities": 59982700000,
            "preferredStock": 0,
            "commonStock": 3359300000,
            "retainedEarnings": 10687800000,
            "accumulatedOtherComprehensiveIncomeLoss": -85100000,
            "othertotalStockholdersEquity": 6588900000,
            "totalStockholdersEquity": 20550900000,
            "totalEquity": 20774500000,
            "totalLiabilitiesAndStockholdersEquity": 80757200000,
            "minorityInterest": 223600000,
            "totalLiabilitiesAndTotalEquity": 80757200000,
            "totalInvestments": 4164500000,
            "totalDebt": 34431500000,
            "netDebt": 34038800000,
            "link": "https://www.sec.gov/Archives/edgar/data/4904/000000490421000010/0000004904-21-000010-index.htm",
            "finalLink": "https://www.sec.gov/Archives/edgar/data/4904/000000490421000010/aep-20201231.htm"
        }
    ]
}